discoutils/__init__.py
discoutils/help_cmds.py
discoutils/random_things.py
discoutils/cogs/__init__.py
discoutils/cogs/fun.py
discoutils/cogs/moderation.py
discoutils-0.0.3.4.dist-info/LICENSE
discoutils-0.0.3.4.dist-info/METADATA
discoutils-0.0.3.4.dist-info/WHEEL
discoutils-0.0.3.4.dist-info/top_level.txt
discoutils-0.0.3.4.dist-info/RECORD
