Metadata-Version: 2.1
Name: discoutils
Version: 0.0.3.4
Summary: Some utilities for discord.py. Making Discord bot development easier.
Home-page: https://github.com/Rishiraj0100/discoutils
Author: Rishi Raj
Author-email: 
License: MIT
Keywords: discord discord-py discord-bot utils utility
Platform: UNKNOWN
Classifier: License :: OSI Approved :: MIT License
Classifier: Programming Language :: Python :: 3.8
Requires-Python: >=3.8
Requires-Dist: discord.py (<2,>=1)
